CHANGES.md
LICENSE
MANIFEST.in
README.rst
setup.py
Arachne_Strahi.egg-info/PKG-INFO
Arachne_Strahi.egg-info/SOURCES.txt
Arachne_Strahi.egg-info/dependency_links.txt
Arachne_Strahi.egg-info/requires.txt
Arachne_Strahi.egg-info/top_level.txt
arachne/__init__.py
arachne/default_settings.py
arachne/endpoints.py
arachne/exceptions.py
arachne/extensions.py
arachne/flaskapp.py
arachne/scrapy_utils.py
arachne/tests/BaseFlaskApp.py
arachne/tests/__init__.py
arachne/tests/test_default_settings.py
arachne/tests/test_endpoints.py
arachne/tests/test_extensions.py
arachne/tests/test_flaskapp.py
arachne/tests/test_scrapy_utils.py
arachne/tests/test_settings.py